{
  "id": "253-134-S--2020-05-05--13.14.53--detections",
  "model": "ResNet50_COCO_best_v2.0.1.h5",
  "summary": {
    "total": 2,
    "car": 2
  },
  "253-134-S--2020-05-05--13.14.53--detections--1--car--48.3--12x10--95.35v107.45": {
    "type": "car",
    "id": "253-134-S--2020-05-05--13.14.53--detections--1--car--48.3--12x10--95.35v107.45",
    "percentage_probability": 48.33899438381195,
    "box_points": [
      95,
      35,
      107,
      45
    ]
  },
  "253-134-S--2020-05-05--13.14.53--detections--2--car--42.2--19x12--150.53v169.65": {
    "type": "car",
    "id": "253-134-S--2020-05-05--13.14.53--detections--2--car--42.2--19x12--150.53v169.65",
    "percentage_probability": 42.23011136054993,
    "box_points": [
      150,
      53,
      169,
      65
    ]
  }
}
