{
  "id": "253-134-S--2020-05-05--13.33.17--detections",
  "model": "ResNet50_COCO_best_v2.0.1.h5",
  "summary": {
    "total": 4,
    "car": 4
  },
  "253-134-S--2020-05-05--13.33.17--detections--1--car--54.5--12x7--88.51v100.58": {
    "type": "car",
    "id": "253-134-S--2020-05-05--13.33.17--detections--1--car--54.5--12x7--88.51v100.58",
    "percentage_probability": 54.459065198898315,
    "box_points": [
      88,
      51,
      100,
      58
    ]
  },
  "253-134-S--2020-05-05--13.33.17--detections--2--car--62.6--14x12--75.51v89.63": {
    "type": "car",
    "id": "253-134-S--2020-05-05--13.33.17--detections--2--car--62.6--14x12--75.51v89.63",
    "percentage_probability": 62.631773948669434,
    "box_points": [
      75,
      51,
      89,
      63
    ]
  },
  "253-134-S--2020-05-05--13.33.17--detections--3--car--81.9--16x12--106.58v122.70": {
    "type": "car",
    "id": "253-134-S--2020-05-05--13.33.17--detections--3--car--81.9--16x12--106.58v122.70",
    "percentage_probability": 81.93522691726685,
    "box_points": [
      106,
      58,
      122,
      70
    ]
  },
  "253-134-S--2020-05-05--13.33.17--detections--4--car--83.5--15x11--67.62v82.73": {
    "type": "car",
    "id": "253-134-S--2020-05-05--13.33.17--detections--4--car--83.5--15x11--67.62v82.73",
    "percentage_probability": 83.53670835494995,
    "box_points": [
      67,
      62,
      82,
      73
    ]
  }
}
