{
  "id": "253-134-S--2020-05-05--13.30.38--detections",
  "model": "ResNet50_COCO_best_v2.0.1.h5",
  "summary": {
    "total": 8,
    "car": 7,
    "person": 1
  },
  "253-134-S--2020-05-05--13.30.38--detections--1--car--44.1--8x6--103.36v111.42": {
    "type": "car",
    "id": "253-134-S--2020-05-05--13.30.38--detections--1--car--44.1--8x6--103.36v111.42",
    "percentage_probability": 44.05798017978668,
    "box_points": [
      103,
      36,
      111,
      42
    ]
  },
  "253-134-S--2020-05-05--13.30.38--detections--2--car--39.7--9x7--52.45v61.52": {
    "type": "car",
    "id": "253-134-S--2020-05-05--13.30.38--detections--2--car--39.7--9x7--52.45v61.52",
    "percentage_probability": 39.65498507022858,
    "box_points": [
      52,
      45,
      61,
      52
    ]
  },
  "253-134-S--2020-05-05--13.30.38--detections--3--car--47.0--12x7--107.46v119.53": {
    "type": "car",
    "id": "253-134-S--2020-05-05--13.30.38--detections--3--car--47.0--12x7--107.46v119.53",
    "percentage_probability": 46.97788059711456,
    "box_points": [
      107,
      46,
      119,
      53
    ]
  },
  "253-134-S--2020-05-05--13.30.38--detections--4--car--59.2--12x10--68.46v80.56": {
    "type": "car",
    "id": "253-134-S--2020-05-05--13.30.38--detections--4--car--59.2--12x10--68.46v80.56",
    "percentage_probability": 59.23168659210205,
    "box_points": [
      68,
      46,
      80,
      56
    ]
  },
  "253-134-S--2020-05-05--13.30.38--detections--5--car--53.6--21x17--73.77v94.94": {
    "type": "car",
    "id": "253-134-S--2020-05-05--13.30.38--detections--5--car--53.6--21x17--73.77v94.94",
    "percentage_probability": 53.56436371803284,
    "box_points": [
      73,
      77,
      94,
      94
    ]
  },
  "253-134-S--2020-05-05--13.30.38--detections--6--person--25.4--6x15--24.127v30.142": {
    "type": "person",
    "id": "253-134-S--2020-05-05--13.30.38--detections--6--person--25.4--6x15--24.127v30.142",
    "percentage_probability": 25.373291969299316,
    "box_points": [
      24,
      127,
      30,
      142
    ]
  },
  "253-134-S--2020-05-05--13.30.38--detections--7--car--62.6--21x16--107.56v128.72": {
    "type": "car",
    "id": "253-134-S--2020-05-05--13.30.38--detections--7--car--62.6--21x16--107.56v128.72",
    "percentage_probability": 62.607407569885254,
    "box_points": [
      107,
      56,
      128,
      72
    ]
  },
  "253-134-S--2020-05-05--13.30.38--detections--8--car--49.6--30x21--114.79v144.100": {
    "type": "car",
    "id": "253-134-S--2020-05-05--13.30.38--detections--8--car--49.6--30x21--114.79v144.100",
    "percentage_probability": 49.61041808128357,
    "box_points": [
      114,
      79,
      144,
      100
    ]
  }
}
