{
  "id": "253-134-S--2020-05-05--13.50.16--detections",
  "model": "ResNet50_COCO_best_v2.0.1.h5",
  "summary": {
    "total": 6,
    "car": 6
  },
  "253-134-S--2020-05-05--13.50.16--detections--1--car--67.6--17x10--129.52v146.62": {
    "type": "car",
    "id": "253-134-S--2020-05-05--13.50.16--detections--1--car--67.6--17x10--129.52v146.62",
    "percentage_probability": 67.6075279712677,
    "box_points": [
      129,
      52,
      146,
      62
    ]
  },
  "253-134-S--2020-05-05--13.50.16--detections--2--car--69.9--18x10--151.52v169.62": {
    "type": "car",
    "id": "253-134-S--2020-05-05--13.50.16--detections--2--car--69.9--18x10--151.52v169.62",
    "percentage_probability": 69.93077993392944,
    "box_points": [
      151,
      52,
      169,
      62
    ]
  },
  "253-134-S--2020-05-05--13.50.16--detections--3--car--69.0--16x14--84.59v100.73": {
    "type": "car",
    "id": "253-134-S--2020-05-05--13.50.16--detections--3--car--69.0--16x14--84.59v100.73",
    "percentage_probability": 69.0345823764801,
    "box_points": [
      84,
      59,
      100,
      73
    ]
  },
  "253-134-S--2020-05-05--13.50.16--detections--4--car--75.4--22x17--120.62v142.79": {
    "type": "car",
    "id": "253-134-S--2020-05-05--13.50.16--detections--4--car--75.4--22x17--120.62v142.79",
    "percentage_probability": 75.44361352920532,
    "box_points": [
      120,
      62,
      142,
      79
    ]
  },
  "253-134-S--2020-05-05--13.50.16--detections--5--car--80.1--26x16--164.64v190.80": {
    "type": "car",
    "id": "253-134-S--2020-05-05--13.50.16--detections--5--car--80.1--26x16--164.64v190.80",
    "percentage_probability": 80.11508584022522,
    "box_points": [
      164,
      64,
      190,
      80
    ]
  },
  "253-134-S--2020-05-05--13.50.16--detections--6--car--84.1--29x23--83.88v112.111": {
    "type": "car",
    "id": "253-134-S--2020-05-05--13.50.16--detections--6--car--84.1--29x23--83.88v112.111",
    "percentage_probability": 84.14803743362427,
    "box_points": [
      83,
      88,
      112,
      111
    ]
  }
}
