{
  "id": "253-134-S--2020-05-05--13.37.35--detections",
  "model": "ResNet50_COCO_best_v2.0.1.h5",
  "summary": {
    "total": 4,
    "car": 3,
    "person": 1
  },
  "253-134-S--2020-05-05--13.37.35--detections--1--car--66.0--21x11--175.61v196.72": {
    "type": "car",
    "id": "253-134-S--2020-05-05--13.37.35--detections--1--car--66.0--21x11--175.61v196.72",
    "percentage_probability": 66.031813621521,
    "box_points": [
      175,
      61,
      196,
      72
    ]
  },
  "253-134-S--2020-05-05--13.37.35--detections--2--person--67.3--9x14--5.225v14.239": {
    "type": "person",
    "id": "253-134-S--2020-05-05--13.37.35--detections--2--person--67.3--9x14--5.225v14.239",
    "percentage_probability": 67.28823184967041,
    "box_points": [
      5,
      225,
      14,
      239
    ]
  },
  "253-134-S--2020-05-05--13.37.35--detections--3--car--96.0--45x21--262.86v307.107": {
    "type": "car",
    "id": "253-134-S--2020-05-05--13.37.35--detections--3--car--96.0--45x21--262.86v307.107",
    "percentage_probability": 95.99368572235107,
    "box_points": [
      262,
      86,
      307,
      107
    ]
  },
  "253-134-S--2020-05-05--13.37.35--detections--4--car--83.5--76x47--245.120v321.167": {
    "type": "car",
    "id": "253-134-S--2020-05-05--13.37.35--detections--4--car--83.5--76x47--245.120v321.167",
    "percentage_probability": 83.46010446548462,
    "box_points": [
      245,
      120,
      321,
      167
    ]
  }
}
