{
  "id": "253-134-S--2020-05-05--13.18.22--detections",
  "model": "ResNet50_COCO_best_v2.0.1.h5",
  "summary": {
    "total": 9,
    "car": 8,
    "bus": 1
  },
  "253-134-S--2020-05-05--13.18.22--detections--1--car--27.5--9x10--92.37v101.47": {
    "type": "car",
    "id": "253-134-S--2020-05-05--13.18.22--detections--1--car--27.5--9x10--92.37v101.47",
    "percentage_probability": 27.523139119148254,
    "box_points": [
      92,
      37,
      101,
      47
    ]
  },
  "253-134-S--2020-05-05--13.18.22--detections--2--car--42.4--11x8--97.38v108.46": {
    "type": "car",
    "id": "253-134-S--2020-05-05--13.18.22--detections--2--car--42.4--11x8--97.38v108.46",
    "percentage_probability": 42.372891306877136,
    "box_points": [
      97,
      38,
      108,
      46
    ]
  },
  "253-134-S--2020-05-05--13.18.22--detections--3--car--27.8--14x12--96.38v110.50": {
    "type": "car",
    "id": "253-134-S--2020-05-05--13.18.22--detections--3--car--27.8--14x12--96.38v110.50",
    "percentage_probability": 27.819129824638367,
    "box_points": [
      96,
      38,
      110,
      50
    ]
  },
  "253-134-S--2020-05-05--13.18.22--detections--4--car--59.9--12x9--128.42v140.51": {
    "type": "car",
    "id": "253-134-S--2020-05-05--13.18.22--detections--4--car--59.9--12x9--128.42v140.51",
    "percentage_probability": 59.92649793624878,
    "box_points": [
      128,
      42,
      140,
      51
    ]
  },
  "253-134-S--2020-05-05--13.18.22--detections--5--car--26.8--13x8--96.44v109.52": {
    "type": "car",
    "id": "253-134-S--2020-05-05--13.18.22--detections--5--car--26.8--13x8--96.44v109.52",
    "percentage_probability": 26.771339774131775,
    "box_points": [
      96,
      44,
      109,
      52
    ]
  },
  "253-134-S--2020-05-05--13.18.22--detections--6--car--60.9--12x6--101.46v113.52": {
    "type": "car",
    "id": "253-134-S--2020-05-05--13.18.22--detections--6--car--60.9--12x6--101.46v113.52",
    "percentage_probability": 60.93635559082031,
    "box_points": [
      101,
      46,
      113,
      52
    ]
  },
  "253-134-S--2020-05-05--13.18.22--detections--7--car--44.1--25x12--71.33v96.45": {
    "type": "car",
    "id": "253-134-S--2020-05-05--13.18.22--detections--7--car--44.1--25x12--71.33v96.45",
    "percentage_probability": 44.13585066795349,
    "box_points": [
      71,
      33,
      96,
      45
    ]
  },
  "253-134-S--2020-05-05--13.18.22--detections--8--car--63.0--55x27--216.80v271.107": {
    "type": "car",
    "id": "253-134-S--2020-05-05--13.18.22--detections--8--car--63.0--55x27--216.80v271.107",
    "percentage_probability": 63.02635669708252,
    "box_points": [
      216,
      80,
      271,
      107
    ]
  },
  "253-134-S--2020-05-05--13.18.22--detections--9--bus--58.2--54x27--216.80v270.107": {
    "type": "bus",
    "id": "253-134-S--2020-05-05--13.18.22--detections--9--bus--58.2--54x27--216.80v270.107",
    "percentage_probability": 58.227378129959106,
    "box_points": [
      216,
      80,
      270,
      107
    ]
  }
}
