{
  "id": "253-134-S--2020-05-05--13.37.39--detections",
  "model": "ResNet50_COCO_best_v2.0.1.h5",
  "summary": {
    "total": 4,
    "car": 4
  },
  "253-134-S--2020-05-05--13.37.39--detections--1--car--71.0--15x13--79.52v94.65": {
    "type": "car",
    "id": "253-134-S--2020-05-05--13.37.39--detections--1--car--71.0--15x13--79.52v94.65",
    "percentage_probability": 71.00029587745667,
    "box_points": [
      79,
      52,
      94,
      65
    ]
  },
  "253-134-S--2020-05-05--13.37.39--detections--2--car--86.2--21x15--144.46v165.61": {
    "type": "car",
    "id": "253-134-S--2020-05-05--13.37.39--detections--2--car--86.2--21x15--144.46v165.61",
    "percentage_probability": 86.2030029296875,
    "box_points": [
      144,
      46,
      165,
      61
    ]
  },
  "253-134-S--2020-05-05--13.37.39--detections--3--car--95.2--30x22--321.104v351.126": {
    "type": "car",
    "id": "253-134-S--2020-05-05--13.37.39--detections--3--car--95.2--30x22--321.104v351.126",
    "percentage_probability": 95.1879620552063,
    "box_points": [
      321,
      104,
      351,
      126
    ]
  },
  "253-134-S--2020-05-05--13.37.39--detections--4--car--77.4--67x50--178.126v245.176": {
    "type": "car",
    "id": "253-134-S--2020-05-05--13.37.39--detections--4--car--77.4--67x50--178.126v245.176",
    "percentage_probability": 77.39477157592773,
    "box_points": [
      178,
      126,
      245,
      176
    ]
  }
}
