{
  "id": "253-134-S--2020-05-05--13.49.23--detections",
  "model": "ResNet50_COCO_best_v2.0.1.h5",
  "summary": {
    "total": 5,
    "car": 4,
    "person": 1
  },
  "253-134-S--2020-05-05--13.49.23--detections--1--car--26.2--9x8--72.40v81.48": {
    "type": "car",
    "id": "253-134-S--2020-05-05--13.49.23--detections--1--car--26.2--9x8--72.40v81.48",
    "percentage_probability": 26.241353154182434,
    "box_points": [
      72,
      40,
      81,
      48
    ]
  },
  "253-134-S--2020-05-05--13.49.23--detections--2--car--31.8--11x7--99.44v110.51": {
    "type": "car",
    "id": "253-134-S--2020-05-05--13.49.23--detections--2--car--31.8--11x7--99.44v110.51",
    "percentage_probability": 31.75039291381836,
    "box_points": [
      99,
      44,
      110,
      51
    ]
  },
  "253-134-S--2020-05-05--13.49.23--detections--3--car--77.9--18x12--141.55v159.67": {
    "type": "car",
    "id": "253-134-S--2020-05-05--13.49.23--detections--3--car--77.9--18x12--141.55v159.67",
    "percentage_probability": 77.91255712509155,
    "box_points": [
      141,
      55,
      159,
      67
    ]
  },
  "253-134-S--2020-05-05--13.49.23--detections--4--person--26.0--5x12--26.117v31.129": {
    "type": "person",
    "id": "253-134-S--2020-05-05--13.49.23--detections--4--person--26.0--5x12--26.117v31.129",
    "percentage_probability": 26.048752665519714,
    "box_points": [
      26,
      117,
      31,
      129
    ]
  },
  "253-134-S--2020-05-05--13.49.23--detections--5--car--48.1--35x29--316.118v351.147": {
    "type": "car",
    "id": "253-134-S--2020-05-05--13.49.23--detections--5--car--48.1--35x29--316.118v351.147",
    "percentage_probability": 48.066967725753784,
    "box_points": [
      316,
      118,
      351,
      147
    ]
  }
}
