{
  "id": "253-134-S--2020-05-05--13.37.16--detections",
  "model": "ResNet50_COCO_best_v2.0.1.h5",
  "summary": {
    "total": 6,
    "car": 6
  },
  "253-134-S--2020-05-05--13.37.16--detections--1--car--61.3--15x9--134.47v149.56": {
    "type": "car",
    "id": "253-134-S--2020-05-05--13.37.16--detections--1--car--61.3--15x9--134.47v149.56",
    "percentage_probability": 61.25941276550293,
    "box_points": [
      134,
      47,
      149,
      56
    ]
  },
  "253-134-S--2020-05-05--13.37.16--detections--2--car--72.7--18x10--171.52v189.62": {
    "type": "car",
    "id": "253-134-S--2020-05-05--13.37.16--detections--2--car--72.7--18x10--171.52v189.62",
    "percentage_probability": 72.73792028427124,
    "box_points": [
      171,
      52,
      189,
      62
    ]
  },
  "253-134-S--2020-05-05--13.37.16--detections--3--car--83.4--21x11--144.57v165.68": {
    "type": "car",
    "id": "253-134-S--2020-05-05--13.37.16--detections--3--car--83.4--21x11--144.57v165.68",
    "percentage_probability": 83.4012508392334,
    "box_points": [
      144,
      57,
      165,
      68
    ]
  },
  "253-134-S--2020-05-05--13.37.16--detections--4--car--76.6--23x14--120.65v143.79": {
    "type": "car",
    "id": "253-134-S--2020-05-05--13.37.16--detections--4--car--76.6--23x14--120.65v143.79",
    "percentage_probability": 76.60572528839111,
    "box_points": [
      120,
      65,
      143,
      79
    ]
  },
  "253-134-S--2020-05-05--13.37.16--detections--5--car--43.8--18x16--87.59v105.75": {
    "type": "car",
    "id": "253-134-S--2020-05-05--13.37.16--detections--5--car--43.8--18x16--87.59v105.75",
    "percentage_probability": 43.7545508146286,
    "box_points": [
      87,
      59,
      105,
      75
    ]
  },
  "253-134-S--2020-05-05--13.37.16--detections--6--car--92.4--116x87--225.150v341.237": {
    "type": "car",
    "id": "253-134-S--2020-05-05--13.37.16--detections--6--car--92.4--116x87--225.150v341.237",
    "percentage_probability": 92.38272309303284,
    "box_points": [
      225,
      150,
      341,
      237
    ]
  }
}
