{
  "id": "253-134-S--2020-05-05--13.15.50--detections",
  "model": "ResNet50_COCO_best_v2.0.1.h5",
  "summary": {
    "total": 4,
    "car": 4
  },
  "253-134-S--2020-05-05--13.15.50--detections--1--car--36.1--14x8--120.43v134.51": {
    "type": "car",
    "id": "253-134-S--2020-05-05--13.15.50--detections--1--car--36.1--14x8--120.43v134.51",
    "percentage_probability": 36.10302209854126,
    "box_points": [
      120,
      43,
      134,
      51
    ]
  },
  "253-134-S--2020-05-05--13.15.50--detections--2--car--50.1--13x9--28.60v41.69": {
    "type": "car",
    "id": "253-134-S--2020-05-05--13.15.50--detections--2--car--50.1--13x9--28.60v41.69",
    "percentage_probability": 50.05183219909668,
    "box_points": [
      28,
      60,
      41,
      69
    ]
  },
  "253-134-S--2020-05-05--13.15.50--detections--3--car--32.5--11x6--4.87v15.93": {
    "type": "car",
    "id": "253-134-S--2020-05-05--13.15.50--detections--3--car--32.5--11x6--4.87v15.93",
    "percentage_probability": 32.527899742126465,
    "box_points": [
      4,
      87,
      15,
      93
    ]
  },
  "253-134-S--2020-05-05--13.15.50--detections--4--car--87.8--31x24--147.76v178.100": {
    "type": "car",
    "id": "253-134-S--2020-05-05--13.15.50--detections--4--car--87.8--31x24--147.76v178.100",
    "percentage_probability": 87.79070377349854,
    "box_points": [
      147,
      76,
      178,
      100
    ]
  }
}
