{
  "id": "253-134-S--2020-05-05--13.24.55--detections",
  "model": "ResNet50_COCO_best_v2.0.1.h5",
  "summary": {
    "total": 6,
    "car": 6
  },
  "253-134-S--2020-05-05--13.24.55--detections--1--car--74.7--16x12--77.61v93.73": {
    "type": "car",
    "id": "253-134-S--2020-05-05--13.24.55--detections--1--car--74.7--16x12--77.61v93.73",
    "percentage_probability": 74.66997504234314,
    "box_points": [
      77,
      61,
      93,
      73
    ]
  },
  "253-134-S--2020-05-05--13.24.55--detections--2--car--26.4--19x13--171.55v190.68": {
    "type": "car",
    "id": "253-134-S--2020-05-05--13.24.55--detections--2--car--26.4--19x13--171.55v190.68",
    "percentage_probability": 26.44997239112854,
    "box_points": [
      171,
      55,
      190,
      68
    ]
  },
  "253-134-S--2020-05-05--13.24.55--detections--3--car--36.7--26x16--150.57v176.73": {
    "type": "car",
    "id": "253-134-S--2020-05-05--13.24.55--detections--3--car--36.7--26x16--150.57v176.73",
    "percentage_probability": 36.70188784599304,
    "box_points": [
      150,
      57,
      176,
      73
    ]
  },
  "253-134-S--2020-05-05--13.24.55--detections--4--car--79.5--28x13--220.65v248.78": {
    "type": "car",
    "id": "253-134-S--2020-05-05--13.24.55--detections--4--car--79.5--28x13--220.65v248.78",
    "percentage_probability": 79.49995994567871,
    "box_points": [
      220,
      65,
      248,
      78
    ]
  },
  "253-134-S--2020-05-05--13.24.55--detections--5--car--76.8--23x21--75.76v98.97": {
    "type": "car",
    "id": "253-134-S--2020-05-05--13.24.55--detections--5--car--76.8--23x21--75.76v98.97",
    "percentage_probability": 76.83898210525513,
    "box_points": [
      75,
      76,
      98,
      97
    ]
  },
  "253-134-S--2020-05-05--13.24.55--detections--6--car--95.0--42x22--239.80v281.102": {
    "type": "car",
    "id": "253-134-S--2020-05-05--13.24.55--detections--6--car--95.0--42x22--239.80v281.102",
    "percentage_probability": 94.96275186538696,
    "box_points": [
      239,
      80,
      281,
      102
    ]
  }
}
