{
  "id": "253-134-S--2020-05-05--13.58.22--detections",
  "model": "ResNet50_COCO_best_v2.0.1.h5",
  "summary": {
    "total": 5,
    "car": 5
  },
  "253-134-S--2020-05-05--13.58.22--detections--1--car--46.1--11x9--70.43v81.52": {
    "type": "car",
    "id": "253-134-S--2020-05-05--13.58.22--detections--1--car--46.1--11x9--70.43v81.52",
    "percentage_probability": 46.095794439315796,
    "box_points": [
      70,
      43,
      81,
      52
    ]
  },
  "253-134-S--2020-05-05--13.58.22--detections--2--car--77.3--14x12--78.53v92.65": {
    "type": "car",
    "id": "253-134-S--2020-05-05--13.58.22--detections--2--car--77.3--14x12--78.53v92.65",
    "percentage_probability": 77.30386257171631,
    "box_points": [
      78,
      53,
      92,
      65
    ]
  },
  "253-134-S--2020-05-05--13.58.22--detections--3--car--84.4--15x12--96.51v111.63": {
    "type": "car",
    "id": "253-134-S--2020-05-05--13.58.22--detections--3--car--84.4--15x12--96.51v111.63",
    "percentage_probability": 84.39575433731079,
    "box_points": [
      96,
      51,
      111,
      63
    ]
  },
  "253-134-S--2020-05-05--13.58.22--detections--4--car--42.3--29x18--141.75v170.93": {
    "type": "car",
    "id": "253-134-S--2020-05-05--13.58.22--detections--4--car--42.3--29x18--141.75v170.93",
    "percentage_probability": 42.33989119529724,
    "box_points": [
      141,
      75,
      170,
      93
    ]
  },
  "253-134-S--2020-05-05--13.58.22--detections--5--car--92.6--34x28--92.94v126.122": {
    "type": "car",
    "id": "253-134-S--2020-05-05--13.58.22--detections--5--car--92.6--34x28--92.94v126.122",
    "percentage_probability": 92.61047840118408,
    "box_points": [
      92,
      94,
      126,
      122
    ]
  }
}
