{
  "id": "253-134-S--2020-05-05--13.42.41--detections",
  "model": "ResNet50_COCO_best_v2.0.1.h5",
  "summary": {
    "total": 6,
    "car": 6
  },
  "253-134-S--2020-05-05--13.42.41--detections--1--car--32.5--8x8--90.32v98.40": {
    "type": "car",
    "id": "253-134-S--2020-05-05--13.42.41--detections--1--car--32.5--8x8--90.32v98.40",
    "percentage_probability": 32.50660300254822,
    "box_points": [
      90,
      32,
      98,
      40
    ]
  },
  "253-134-S--2020-05-05--13.42.41--detections--2--car--31.1--9x7--116.42v125.49": {
    "type": "car",
    "id": "253-134-S--2020-05-05--13.42.41--detections--2--car--31.1--9x7--116.42v125.49",
    "percentage_probability": 31.107425689697266,
    "box_points": [
      116,
      42,
      125,
      49
    ]
  },
  "253-134-S--2020-05-05--13.42.41--detections--3--car--46.6--11x7--101.45v112.52": {
    "type": "car",
    "id": "253-134-S--2020-05-05--13.42.41--detections--3--car--46.6--11x7--101.45v112.52",
    "percentage_probability": 46.57560884952545,
    "box_points": [
      101,
      45,
      112,
      52
    ]
  },
  "253-134-S--2020-05-05--13.42.41--detections--4--car--96.4--35x17--213.72v248.89": {
    "type": "car",
    "id": "253-134-S--2020-05-05--13.42.41--detections--4--car--96.4--35x17--213.72v248.89",
    "percentage_probability": 96.43881320953369,
    "box_points": [
      213,
      72,
      248,
      89
    ]
  },
  "253-134-S--2020-05-05--13.42.41--detections--5--car--75.4--16x21--69.144v85.165": {
    "type": "car",
    "id": "253-134-S--2020-05-05--13.42.41--detections--5--car--75.4--16x21--69.144v85.165",
    "percentage_probability": 75.35834312438965,
    "box_points": [
      69,
      144,
      85,
      165
    ]
  },
  "253-134-S--2020-05-05--13.42.41--detections--6--car--96.4--43x34--102.100v145.134": {
    "type": "car",
    "id": "253-134-S--2020-05-05--13.42.41--detections--6--car--96.4--43x34--102.100v145.134",
    "percentage_probability": 96.36342525482178,
    "box_points": [
      102,
      100,
      145,
      134
    ]
  }
}
