{
  "id": "253-134-S--2020-05-05--13.50.17--detections",
  "model": "ResNet50_COCO_best_v2.0.1.h5",
  "summary": {
    "total": 6,
    "car": 6
  },
  "253-134-S--2020-05-05--13.50.17--detections--1--car--28.0--10x7--110.41v120.48": {
    "type": "car",
    "id": "253-134-S--2020-05-05--13.50.17--detections--1--car--28.0--10x7--110.41v120.48",
    "percentage_probability": 27.970272302627563,
    "box_points": [
      110,
      41,
      120,
      48
    ]
  },
  "253-134-S--2020-05-05--13.50.17--detections--2--car--46.4--11x7--99.43v110.50": {
    "type": "car",
    "id": "253-134-S--2020-05-05--13.50.17--detections--2--car--46.4--11x7--99.43v110.50",
    "percentage_probability": 46.366679668426514,
    "box_points": [
      99,
      43,
      110,
      50
    ]
  },
  "253-134-S--2020-05-05--13.50.17--detections--3--car--70.3--14x9--112.47v126.56": {
    "type": "car",
    "id": "253-134-S--2020-05-05--13.50.17--detections--3--car--70.3--14x9--112.47v126.56",
    "percentage_probability": 70.34692168235779,
    "box_points": [
      112,
      47,
      126,
      56
    ]
  },
  "253-134-S--2020-05-05--13.50.17--detections--4--car--92.2--24x14--165.61v189.75": {
    "type": "car",
    "id": "253-134-S--2020-05-05--13.50.17--detections--4--car--92.2--24x14--165.61v189.75",
    "percentage_probability": 92.23709106445312,
    "box_points": [
      165,
      61,
      189,
      75
    ]
  },
  "253-134-S--2020-05-05--13.50.17--detections--5--car--96.8--50x38--144.105v194.143": {
    "type": "car",
    "id": "253-134-S--2020-05-05--13.50.17--detections--5--car--96.8--50x38--144.105v194.143",
    "percentage_probability": 96.8219518661499,
    "box_points": [
      144,
      105,
      194,
      143
    ]
  },
  "253-134-S--2020-05-05--13.50.17--detections--6--car--44.8--62x71--297.140v359.211": {
    "type": "car",
    "id": "253-134-S--2020-05-05--13.50.17--detections--6--car--44.8--62x71--297.140v359.211",
    "percentage_probability": 44.810593128204346,
    "box_points": [
      297,
      140,
      359,
      211
    ]
  }
}
