{
  "id": "253-134-S--2020-05-05--13.23.13--detections",
  "model": "ResNet50_COCO_best_v2.0.1.h5",
  "summary": {
    "total": 3,
    "car": 2,
    "person": 1
  },
  "253-134-S--2020-05-05--13.23.13--detections--1--car--46.1--15x11--83.58v98.69": {
    "type": "car",
    "id": "253-134-S--2020-05-05--13.23.13--detections--1--car--46.1--15x11--83.58v98.69",
    "percentage_probability": 46.11097276210785,
    "box_points": [
      83,
      58,
      98,
      69
    ]
  },
  "253-134-S--2020-05-05--13.23.13--detections--2--person--37.6--9x20--0.219v9.239": {
    "type": "person",
    "id": "253-134-S--2020-05-05--13.23.13--detections--2--person--37.6--9x20--0.219v9.239",
    "percentage_probability": 37.59659826755524,
    "box_points": [
      0,
      219,
      9,
      239
    ]
  },
  "253-134-S--2020-05-05--13.23.13--detections--3--car--97.4--59x25--288.95v347.120": {
    "type": "car",
    "id": "253-134-S--2020-05-05--13.23.13--detections--3--car--97.4--59x25--288.95v347.120",
    "percentage_probability": 97.43027687072754,
    "box_points": [
      288,
      95,
      347,
      120
    ]
  }
}
