{
  "id": "253-134-S--2020-05-05--13.33.23--detections",
  "model": "ResNet50_COCO_best_v2.0.1.h5",
  "summary": {
    "total": 7,
    "car": 6,
    "person": 1
  },
  "253-134-S--2020-05-05--13.33.23--detections--1--car--58.3--11x7--123.41v134.48": {
    "type": "car",
    "id": "253-134-S--2020-05-05--13.33.23--detections--1--car--58.3--11x7--123.41v134.48",
    "percentage_probability": 58.344024419784546,
    "box_points": [
      123,
      41,
      134,
      48
    ]
  },
  "253-134-S--2020-05-05--13.33.23--detections--2--car--88.0--16x12--132.45v148.57": {
    "type": "car",
    "id": "253-134-S--2020-05-05--13.33.23--detections--2--car--88.0--16x12--132.45v148.57",
    "percentage_probability": 88.01984786987305,
    "box_points": [
      132,
      45,
      148,
      57
    ]
  },
  "253-134-S--2020-05-05--13.33.23--detections--3--car--66.5--20x11--160.48v180.59": {
    "type": "car",
    "id": "253-134-S--2020-05-05--13.33.23--detections--3--car--66.5--20x11--160.48v180.59",
    "percentage_probability": 66.54359102249146,
    "box_points": [
      160,
      48,
      180,
      59
    ]
  },
  "253-134-S--2020-05-05--13.33.23--detections--4--car--31.2--21x13--168.56v189.69": {
    "type": "car",
    "id": "253-134-S--2020-05-05--13.33.23--detections--4--car--31.2--21x13--168.56v189.69",
    "percentage_probability": 31.195536255836487,
    "box_points": [
      168,
      56,
      189,
      69
    ]
  },
  "253-134-S--2020-05-05--13.33.23--detections--5--person--86.2--11x22--43.212v54.234": {
    "type": "person",
    "id": "253-134-S--2020-05-05--13.33.23--detections--5--person--86.2--11x22--43.212v54.234",
    "percentage_probability": 86.1933708190918,
    "box_points": [
      43,
      212,
      54,
      234
    ]
  },
  "253-134-S--2020-05-05--13.33.23--detections--6--car--67.8--29x25--168.56v197.81": {
    "type": "car",
    "id": "253-134-S--2020-05-05--13.33.23--detections--6--car--67.8--29x25--168.56v197.81",
    "percentage_probability": 67.84154772758484,
    "box_points": [
      168,
      56,
      197,
      81
    ]
  },
  "253-134-S--2020-05-05--13.33.23--detections--7--car--68.5--50x33--303.94v353.127": {
    "type": "car",
    "id": "253-134-S--2020-05-05--13.33.23--detections--7--car--68.5--50x33--303.94v353.127",
    "percentage_probability": 68.50017309188843,
    "box_points": [
      303,
      94,
      353,
      127
    ]
  }
}
