{
  "id": "253-134-S--2020-05-05--13.57.17--detections",
  "model": "ResNet50_COCO_best_v2.0.1.h5",
  "summary": {
    "total": 2,
    "car": 2
  },
  "253-134-S--2020-05-05--13.57.17--detections--1--car--72.6--14x12--80.55v94.67": {
    "type": "car",
    "id": "253-134-S--2020-05-05--13.57.17--detections--1--car--72.6--14x12--80.55v94.67",
    "percentage_probability": 72.64312505722046,
    "box_points": [
      80,
      55,
      94,
      67
    ]
  },
  "253-134-S--2020-05-05--13.57.17--detections--2--car--91.2--25x17--130.69v155.86": {
    "type": "car",
    "id": "253-134-S--2020-05-05--13.57.17--detections--2--car--91.2--25x17--130.69v155.86",
    "percentage_probability": 91.20103120803833,
    "box_points": [
      130,
      69,
      155,
      86
    ]
  }
}
