{
  "id": "253-134-S--2020-05-05--13.11.45--detections",
  "model": "ResNet50_COCO_best_v2.0.1.h5",
  "summary": {
    "total": 8,
    "car": 6,
    "person": 2
  },
  "253-134-S--2020-05-05--13.11.45--detections--1--car--35.3--8x8--64.43v72.51": {
    "type": "car",
    "id": "253-134-S--2020-05-05--13.11.45--detections--1--car--35.3--8x8--64.43v72.51",
    "percentage_probability": 35.31389832496643,
    "box_points": [
      64,
      43,
      72,
      51
    ]
  },
  "253-134-S--2020-05-05--13.11.45--detections--2--car--43.7--9x7--79.46v88.53": {
    "type": "car",
    "id": "253-134-S--2020-05-05--13.11.45--detections--2--car--43.7--9x7--79.46v88.53",
    "percentage_probability": 43.730539083480835,
    "box_points": [
      79,
      46,
      88,
      53
    ]
  },
  "253-134-S--2020-05-05--13.11.45--detections--3--car--40.6--13x10--28.59v41.69": {
    "type": "car",
    "id": "253-134-S--2020-05-05--13.11.45--detections--3--car--40.6--13x10--28.59v41.69",
    "percentage_probability": 40.557655692100525,
    "box_points": [
      28,
      59,
      41,
      69
    ]
  },
  "253-134-S--2020-05-05--13.11.45--detections--4--car--65.7--15x13--87.60v102.73": {
    "type": "car",
    "id": "253-134-S--2020-05-05--13.11.45--detections--4--car--65.7--15x13--87.60v102.73",
    "percentage_probability": 65.69265127182007,
    "box_points": [
      87,
      60,
      102,
      73
    ]
  },
  "253-134-S--2020-05-05--13.11.45--detections--5--person--38.1--8x18--8.141v16.159": {
    "type": "person",
    "id": "253-134-S--2020-05-05--13.11.45--detections--5--person--38.1--8x18--8.141v16.159",
    "percentage_probability": 38.11807632446289,
    "box_points": [
      8,
      141,
      16,
      159
    ]
  },
  "253-134-S--2020-05-05--13.11.45--detections--6--car--31.2--23x19--126.65v149.84": {
    "type": "car",
    "id": "253-134-S--2020-05-05--13.11.45--detections--6--car--31.2--23x19--126.65v149.84",
    "percentage_probability": 31.171390414237976,
    "box_points": [
      126,
      65,
      149,
      84
    ]
  },
  "253-134-S--2020-05-05--13.11.45--detections--7--car--72.7--21x17--76.73v97.90": {
    "type": "car",
    "id": "253-134-S--2020-05-05--13.11.45--detections--7--car--72.7--21x17--76.73v97.90",
    "percentage_probability": 72.66107201576233,
    "box_points": [
      76,
      73,
      97,
      90
    ]
  },
  "253-134-S--2020-05-05--13.11.45--detections--8--person--29.3--10x27--5.132v15.159": {
    "type": "person",
    "id": "253-134-S--2020-05-05--13.11.45--detections--8--person--29.3--10x27--5.132v15.159",
    "percentage_probability": 29.343324899673462,
    "box_points": [
      5,
      132,
      15,
      159
    ]
  }
}
