{
  "id": "253-134-S--2020-05-05--13.43.22--detections",
  "model": "ResNet50_COCO_best_v2.0.1.h5",
  "summary": {
    "total": 5,
    "car": 5
  },
  "253-134-S--2020-05-05--13.43.22--detections--1--car--26.8--10x7--119.41v129.48": {
    "type": "car",
    "id": "253-134-S--2020-05-05--13.43.22--detections--1--car--26.8--10x7--119.41v129.48",
    "percentage_probability": 26.753482222557068,
    "box_points": [
      119,
      41,
      129,
      48
    ]
  },
  "253-134-S--2020-05-05--13.43.22--detections--2--car--69.1--16x8--143.52v159.60": {
    "type": "car",
    "id": "253-134-S--2020-05-05--13.43.22--detections--2--car--69.1--16x8--143.52v159.60",
    "percentage_probability": 69.07051801681519,
    "box_points": [
      143,
      52,
      159,
      60
    ]
  },
  "253-134-S--2020-05-05--13.43.22--detections--3--car--45.4--27x15--222.62v249.77": {
    "type": "car",
    "id": "253-134-S--2020-05-05--13.43.22--detections--3--car--45.4--27x15--222.62v249.77",
    "percentage_probability": 45.428648591041565,
    "box_points": [
      222,
      62,
      249,
      77
    ]
  },
  "253-134-S--2020-05-05--13.43.22--detections--4--car--82.6--21x17--98.68v119.85": {
    "type": "car",
    "id": "253-134-S--2020-05-05--13.43.22--detections--4--car--82.6--21x17--98.68v119.85",
    "percentage_probability": 82.57594704627991,
    "box_points": [
      98,
      68,
      119,
      85
    ]
  },
  "253-134-S--2020-05-05--13.43.22--detections--5--car--90.1--33x16--202.68v235.84": {
    "type": "car",
    "id": "253-134-S--2020-05-05--13.43.22--detections--5--car--90.1--33x16--202.68v235.84",
    "percentage_probability": 90.09637832641602,
    "box_points": [
      202,
      68,
      235,
      84
    ]
  }
}
