{
  "id": "253-134-S--2020-05-05--13.53.28--detections",
  "model": "ResNet50_COCO_best_v2.0.1.h5",
  "summary": {
    "total": 7,
    "car": 6,
    "person": 1
  },
  "253-134-S--2020-05-05--13.53.28--detections--1--car--34.3--8x8--83.36v91.44": {
    "type": "car",
    "id": "253-134-S--2020-05-05--13.53.28--detections--1--car--34.3--8x8--83.36v91.44",
    "percentage_probability": 34.329020977020264,
    "box_points": [
      83,
      36,
      91,
      44
    ]
  },
  "253-134-S--2020-05-05--13.53.28--detections--2--car--34.3--9x8--60.40v69.48": {
    "type": "car",
    "id": "253-134-S--2020-05-05--13.53.28--detections--2--car--34.3--9x8--60.40v69.48",
    "percentage_probability": 34.33650732040405,
    "box_points": [
      60,
      40,
      69,
      48
    ]
  },
  "253-134-S--2020-05-05--13.53.28--detections--3--car--44.8--11x8--107.44v118.52": {
    "type": "car",
    "id": "253-134-S--2020-05-05--13.53.28--detections--3--car--44.8--11x8--107.44v118.52",
    "percentage_probability": 44.83832120895386,
    "box_points": [
      107,
      44,
      118,
      52
    ]
  },
  "253-134-S--2020-05-05--13.53.28--detections--4--person--36.7--6x15--15.167v21.182": {
    "type": "person",
    "id": "253-134-S--2020-05-05--13.53.28--detections--4--person--36.7--6x15--15.167v21.182",
    "percentage_probability": 36.726564168930054,
    "box_points": [
      15,
      167,
      21,
      182
    ]
  },
  "253-134-S--2020-05-05--13.53.28--detections--5--car--76.9--17x14--94.50v111.64": {
    "type": "car",
    "id": "253-134-S--2020-05-05--13.53.28--detections--5--car--76.9--17x14--94.50v111.64",
    "percentage_probability": 76.89255475997925,
    "box_points": [
      94,
      50,
      111,
      64
    ]
  },
  "253-134-S--2020-05-05--13.53.28--detections--6--car--92.1--35x23--154.82v189.105": {
    "type": "car",
    "id": "253-134-S--2020-05-05--13.53.28--detections--6--car--92.1--35x23--154.82v189.105",
    "percentage_probability": 92.06221103668213,
    "box_points": [
      154,
      82,
      189,
      105
    ]
  },
  "253-134-S--2020-05-05--13.53.28--detections--7--car--89.7--60x29--260.98v320.127": {
    "type": "car",
    "id": "253-134-S--2020-05-05--13.53.28--detections--7--car--89.7--60x29--260.98v320.127",
    "percentage_probability": 89.70444798469543,
    "box_points": [
      260,
      98,
      320,
      127
    ]
  }
}
