{
  "id": "253-134-S--2020-05-05--13.24.58--detections",
  "model": "ResNet50_COCO_best_v2.0.1.h5",
  "summary": {
    "total": 5,
    "car": 5
  },
  "253-134-S--2020-05-05--13.24.58--detections--1--car--29.1--9x6--101.38v110.44": {
    "type": "car",
    "id": "253-134-S--2020-05-05--13.24.58--detections--1--car--29.1--9x6--101.38v110.44",
    "percentage_probability": 29.111075401306152,
    "box_points": [
      101,
      38,
      110,
      44
    ]
  },
  "253-134-S--2020-05-05--13.24.58--detections--2--car--28.3--12x9--112.41v124.50": {
    "type": "car",
    "id": "253-134-S--2020-05-05--13.24.58--detections--2--car--28.3--12x9--112.41v124.50",
    "percentage_probability": 28.292179107666016,
    "box_points": [
      112,
      41,
      124,
      50
    ]
  },
  "253-134-S--2020-05-05--13.24.58--detections--3--car--29.4--14x8--135.49v149.57": {
    "type": "car",
    "id": "253-134-S--2020-05-05--13.24.58--detections--3--car--29.4--14x8--135.49v149.57",
    "percentage_probability": 29.42487597465515,
    "box_points": [
      135,
      49,
      149,
      57
    ]
  },
  "253-134-S--2020-05-05--13.24.58--detections--4--car--87.4--25x18--109.77v134.95": {
    "type": "car",
    "id": "253-134-S--2020-05-05--13.24.58--detections--4--car--87.4--25x18--109.77v134.95",
    "percentage_probability": 87.38298416137695,
    "box_points": [
      109,
      77,
      134,
      95
    ]
  },
  "253-134-S--2020-05-05--13.24.58--detections--5--car--92.2--40x29--153.77v193.106": {
    "type": "car",
    "id": "253-134-S--2020-05-05--13.24.58--detections--5--car--92.2--40x29--153.77v193.106",
    "percentage_probability": 92.20038652420044,
    "box_points": [
      153,
      77,
      193,
      106
    ]
  }
}
