{
  "id": "253-134-S--2020-05-05--13.27.57--detections",
  "model": "ResNet50_COCO_best_v2.0.1.h5",
  "summary": {
    "total": 9,
    "car": 8,
    "person": 1
  },
  "253-134-S--2020-05-05--13.27.57--detections--1--car--31.1--7x7--70.39v77.46": {
    "type": "car",
    "id": "253-134-S--2020-05-05--13.27.57--detections--1--car--31.1--7x7--70.39v77.46",
    "percentage_probability": 31.114578247070312,
    "box_points": [
      70,
      39,
      77,
      46
    ]
  },
  "253-134-S--2020-05-05--13.27.57--detections--2--car--47.1--9x7--59.41v68.48": {
    "type": "car",
    "id": "253-134-S--2020-05-05--13.27.57--detections--2--car--47.1--9x7--59.41v68.48",
    "percentage_probability": 47.117879986763,
    "box_points": [
      59,
      41,
      68,
      48
    ]
  },
  "253-134-S--2020-05-05--13.27.57--detections--3--car--61.1--13x9--127.46v140.55": {
    "type": "car",
    "id": "253-134-S--2020-05-05--13.27.57--detections--3--car--61.1--13x9--127.46v140.55",
    "percentage_probability": 61.089032888412476,
    "box_points": [
      127,
      46,
      140,
      55
    ]
  },
  "253-134-S--2020-05-05--13.27.57--detections--4--car--46.0--12x12--71.46v83.58": {
    "type": "car",
    "id": "253-134-S--2020-05-05--13.27.57--detections--4--car--46.0--12x12--71.46v83.58",
    "percentage_probability": 45.99367082118988,
    "box_points": [
      71,
      46,
      83,
      58
    ]
  },
  "253-134-S--2020-05-05--13.27.57--detections--5--car--57.2--9x7--83.46v92.53": {
    "type": "car",
    "id": "253-134-S--2020-05-05--13.27.57--detections--5--car--57.2--9x7--83.46v92.53",
    "percentage_probability": 57.153624296188354,
    "box_points": [
      83,
      46,
      92,
      53
    ]
  },
  "253-134-S--2020-05-05--13.27.57--detections--6--car--35.7--14x9--26.60v40.69": {
    "type": "car",
    "id": "253-134-S--2020-05-05--13.27.57--detections--6--car--35.7--14x9--26.60v40.69",
    "percentage_probability": 35.71804165840149,
    "box_points": [
      26,
      60,
      40,
      69
    ]
  },
  "253-134-S--2020-05-05--13.27.57--detections--7--car--25.5--8x11--33.58v41.69": {
    "type": "car",
    "id": "253-134-S--2020-05-05--13.27.57--detections--7--car--25.5--8x11--33.58v41.69",
    "percentage_probability": 25.491344928741455,
    "box_points": [
      33,
      58,
      41,
      69
    ]
  },
  "253-134-S--2020-05-05--13.27.57--detections--8--person--27.7--8x11--16.105v24.116": {
    "type": "person",
    "id": "253-134-S--2020-05-05--13.27.57--detections--8--person--27.7--8x11--16.105v24.116",
    "percentage_probability": 27.676787972450256,
    "box_points": [
      16,
      105,
      24,
      116
    ]
  },
  "253-134-S--2020-05-05--13.27.57--detections--9--car--97.5--45x22--240.79v285.101": {
    "type": "car",
    "id": "253-134-S--2020-05-05--13.27.57--detections--9--car--97.5--45x22--240.79v285.101",
    "percentage_probability": 97.48830795288086,
    "box_points": [
      240,
      79,
      285,
      101
    ]
  }
}
