{
  "id": "253-134-S--2020-05-05--13.34.37--detections",
  "model": "ResNet50_COCO_best_v2.0.1.h5",
  "summary": {
    "total": 8,
    "car": 8
  },
  "253-134-S--2020-05-05--13.34.37--detections--1--car--52.2--9x7--97.43v106.50": {
    "type": "car",
    "id": "253-134-S--2020-05-05--13.34.37--detections--1--car--52.2--9x7--97.43v106.50",
    "percentage_probability": 52.19518542289734,
    "box_points": [
      97,
      43,
      106,
      50
    ]
  },
  "253-134-S--2020-05-05--13.34.37--detections--2--car--50.5--9x6--112.43v121.49": {
    "type": "car",
    "id": "253-134-S--2020-05-05--13.34.37--detections--2--car--50.5--9x6--112.43v121.49",
    "percentage_probability": 50.48394203186035,
    "box_points": [
      112,
      43,
      121,
      49
    ]
  },
  "253-134-S--2020-05-05--13.34.37--detections--3--car--69.6--17x11--125.44v142.55": {
    "type": "car",
    "id": "253-134-S--2020-05-05--13.34.37--detections--3--car--69.6--17x11--125.44v142.55",
    "percentage_probability": 69.63330507278442,
    "box_points": [
      125,
      44,
      142,
      55
    ]
  },
  "253-134-S--2020-05-05--13.34.37--detections--4--car--86.2--15x10--97.54v112.64": {
    "type": "car",
    "id": "253-134-S--2020-05-05--13.34.37--detections--4--car--86.2--15x10--97.54v112.64",
    "percentage_probability": 86.15838289260864,
    "box_points": [
      97,
      54,
      112,
      64
    ]
  },
  "253-134-S--2020-05-05--13.34.37--detections--5--car--85.3--18x13--135.53v153.66": {
    "type": "car",
    "id": "253-134-S--2020-05-05--13.34.37--detections--5--car--85.3--18x13--135.53v153.66",
    "percentage_probability": 85.26151180267334,
    "box_points": [
      135,
      53,
      153,
      66
    ]
  },
  "253-134-S--2020-05-05--13.34.37--detections--6--car--57.1--21x15--93.71v114.86": {
    "type": "car",
    "id": "253-134-S--2020-05-05--13.34.37--detections--6--car--57.1--21x15--93.71v114.86",
    "percentage_probability": 57.06146955490112,
    "box_points": [
      93,
      71,
      114,
      86
    ]
  },
  "253-134-S--2020-05-05--13.34.37--detections--7--car--67.6--52x27--238.89v290.116": {
    "type": "car",
    "id": "253-134-S--2020-05-05--13.34.37--detections--7--car--67.6--52x27--238.89v290.116",
    "percentage_probability": 67.61479377746582,
    "box_points": [
      238,
      89,
      290,
      116
    ]
  },
  "253-134-S--2020-05-05--13.34.37--detections--8--car--98.1--59x41--146.114v205.155": {
    "type": "car",
    "id": "253-134-S--2020-05-05--13.34.37--detections--8--car--98.1--59x41--146.114v205.155",
    "percentage_probability": 98.13942909240723,
    "box_points": [
      146,
      114,
      205,
      155
    ]
  }
}
