{
  "id": "253-134-S--2020-05-05--13.56.06--detections",
  "model": "ResNet50_COCO_best_v2.0.1.h5",
  "summary": {
    "total": 16,
    "car": 15,
    "person": 1
  },
  "253-134-S--2020-05-05--13.56.06--detections--1--car--25.5--11x7--79.36v90.43": {
    "type": "car",
    "id": "253-134-S--2020-05-05--13.56.06--detections--1--car--25.5--11x7--79.36v90.43",
    "percentage_probability": 25.547856092453003,
    "box_points": [
      79,
      36,
      90,
      43
    ]
  },
  "253-134-S--2020-05-05--13.56.06--detections--2--car--37.2--9x10--88.36v97.46": {
    "type": "car",
    "id": "253-134-S--2020-05-05--13.56.06--detections--2--car--37.2--9x10--88.36v97.46",
    "percentage_probability": 37.22376525402069,
    "box_points": [
      88,
      36,
      97,
      46
    ]
  },
  "253-134-S--2020-05-05--13.56.06--detections--3--car--25.5--16x12--92.37v108.49": {
    "type": "car",
    "id": "253-134-S--2020-05-05--13.56.06--detections--3--car--25.5--16x12--92.37v108.49",
    "percentage_probability": 25.491702556610107,
    "box_points": [
      92,
      37,
      108,
      49
    ]
  },
  "253-134-S--2020-05-05--13.56.06--detections--4--car--27.4--19x10--96.38v115.48": {
    "type": "car",
    "id": "253-134-S--2020-05-05--13.56.06--detections--4--car--27.4--19x10--96.38v115.48",
    "percentage_probability": 27.449828386306763,
    "box_points": [
      96,
      38,
      115,
      48
    ]
  },
  "253-134-S--2020-05-05--13.56.06--detections--5--car--46.5--11x10--97.39v108.49": {
    "type": "car",
    "id": "253-134-S--2020-05-05--13.56.06--detections--5--car--46.5--11x10--97.39v108.49",
    "percentage_probability": 46.4503288269043,
    "box_points": [
      97,
      39,
      108,
      49
    ]
  },
  "253-134-S--2020-05-05--13.56.06--detections--6--car--33.8--12x8--103.40v115.48": {
    "type": "car",
    "id": "253-134-S--2020-05-05--13.56.06--detections--6--car--33.8--12x8--103.40v115.48",
    "percentage_probability": 33.780843019485474,
    "box_points": [
      103,
      40,
      115,
      48
    ]
  },
  "253-134-S--2020-05-05--13.56.06--detections--7--car--25.9--9x7--66.44v75.51": {
    "type": "car",
    "id": "253-134-S--2020-05-05--13.56.06--detections--7--car--25.9--9x7--66.44v75.51",
    "percentage_probability": 25.93204975128174,
    "box_points": [
      66,
      44,
      75,
      51
    ]
  },
  "253-134-S--2020-05-05--13.56.06--detections--8--car--53.1--10x7--117.44v127.51": {
    "type": "car",
    "id": "253-134-S--2020-05-05--13.56.06--detections--8--car--53.1--10x7--117.44v127.51",
    "percentage_probability": 53.12439203262329,
    "box_points": [
      117,
      44,
      127,
      51
    ]
  },
  "253-134-S--2020-05-05--13.56.06--detections--9--car--35.3--20x11--151.53v171.64": {
    "type": "car",
    "id": "253-134-S--2020-05-05--13.56.06--detections--9--car--35.3--20x11--151.53v171.64",
    "percentage_probability": 35.28358042240143,
    "box_points": [
      151,
      53,
      171,
      64
    ]
  },
  "253-134-S--2020-05-05--13.56.06--detections--10--person--35.2--6x12--56.135v62.147": {
    "type": "person",
    "id": "253-134-S--2020-05-05--13.56.06--detections--10--person--35.2--6x12--56.135v62.147",
    "percentage_probability": 35.17199158668518,
    "box_points": [
      56,
      135,
      62,
      147
    ]
  },
  "253-134-S--2020-05-05--13.56.06--detections--11--car--74.8--22x14--134.53v156.67": {
    "type": "car",
    "id": "253-134-S--2020-05-05--13.56.06--detections--11--car--74.8--22x14--134.53v156.67",
    "percentage_probability": 74.7936487197876,
    "box_points": [
      134,
      53,
      156,
      67
    ]
  },
  "253-134-S--2020-05-05--13.56.06--detections--12--car--49.8--28x13--140.52v168.65": {
    "type": "car",
    "id": "253-134-S--2020-05-05--13.56.06--detections--12--car--49.8--28x13--140.52v168.65",
    "percentage_probability": 49.79889988899231,
    "box_points": [
      140,
      52,
      168,
      65
    ]
  },
  "253-134-S--2020-05-05--13.56.06--detections--13--car--59.8--15x13--72.57v87.70": {
    "type": "car",
    "id": "253-134-S--2020-05-05--13.56.06--detections--13--car--59.8--15x13--72.57v87.70",
    "percentage_probability": 59.76327061653137,
    "box_points": [
      72,
      57,
      87,
      70
    ]
  },
  "253-134-S--2020-05-05--13.56.06--detections--14--car--81.5--24x16--101.72v125.88": {
    "type": "car",
    "id": "253-134-S--2020-05-05--13.56.06--detections--14--car--81.5--24x16--101.72v125.88",
    "percentage_probability": 81.47469758987427,
    "box_points": [
      101,
      72,
      125,
      88
    ]
  },
  "253-134-S--2020-05-05--13.56.06--detections--15--car--88.9--30x22--81.82v111.104": {
    "type": "car",
    "id": "253-134-S--2020-05-05--13.56.06--detections--15--car--88.9--30x22--81.82v111.104",
    "percentage_probability": 88.91583681106567,
    "box_points": [
      81,
      82,
      111,
      104
    ]
  },
  "253-134-S--2020-05-05--13.56.06--detections--16--car--82.2--29x32--322.94v351.126": {
    "type": "car",
    "id": "253-134-S--2020-05-05--13.56.06--detections--16--car--82.2--29x32--322.94v351.126",
    "percentage_probability": 82.2033941745758,
    "box_points": [
      322,
      94,
      351,
      126
    ]
  }
}
